easyencrypt/__init__.py
easyencrypt/easyencrypt.py
easyencrypt-0.1.0.dist-info/LICENSE
easyencrypt-0.1.0.dist-info/METADATA
easyencrypt-0.1.0.dist-info/WHEEL
easyencrypt-0.1.0.dist-info/top_level.txt
easyencrypt-0.1.0.dist-info/RECORD
