Metadata-Version: 2.1
Name: easyencrypt
Version: 0.1.0
Summary: Hashing, symmetric encryption, and asymmetric encryption functions.
Home-page: https://github.com/WKHAllen/easyencrypt
Author: Will Allen
Author-email: wkhallen@gmail.com
License: MIT
Keywords: encrypt,decrypt,cryptography,security
Platform: UNKNOWN
Classifier: Intended Audience :: Developers
Classifier: Topic :: Security :: Cryptography
Classifier: License :: OSI Approved :: MIT License
Classifier: Programming Language :: Python
Classifier: Programming Language :: Python :: 3
Classifier: Programming Language :: Python :: 3.5
Classifier: Programming Language :: Python :: 3.6
Classifier: Programming Language :: Python :: 3.7
Requires-Dist: cryptography
Requires-Dist: rsa
